pyglimpse/__init__.py
pyglimpse-0.1.0.dist-info/licenses/LICENSE
pyglimpse-0.1.0.dist-info/METADATA
pyglimpse-0.1.0.dist-info/WHEEL
pyglimpse-0.1.0.dist-info/top_level.txt
pyglimpse-0.1.0.dist-info/RECORD
